fzz.cpython-39-darwin.so
pyfzz-0.0.0.dist-info/LICENSE
pyfzz-0.0.0.dist-info/METADATA
pyfzz-0.0.0.dist-info/WHEEL
pyfzz-0.0.0.dist-info/top_level.txt
pyfzz-0.0.0.dist-info/RECORD
